pygoss-0.4.2.dist-info/METADATA
pygoss-0.4.2.dist-info/LICENSE
pygoss-0.4.2.dist-info/WHEEL
pygoss-0.4.2.dist-info/top_level.txt
pygoss-0.4.2.dist-info/entry_points.txt
pygoss-0.4.2.dist-info/RECORD
pygoss.libs/libgomp-a34b3233.so.1.0.0
goss/py.typed
goss/solvers.py
goss/__init__.py
goss/ode.py
goss/_gosscpp.cpython-311-x86_64-linux-gnu.so
goss/codegeneration.py
goss/dolfinutils.py
goss/cuda.py
goss/compilemodule.py
goss/__main__.py
goss/systemsolver.py
goss/cli.py
goss/lib/libgoss.so
goss/lib/cmake/goss/GossTargets.cmake
goss/lib/cmake/goss/GossTargets-release.cmake
goss/lib/cmake/goss/GossConfigVersion.cmake
goss/lib/cmake/goss/GossConfig.cmake
goss/include/goss/AdaptiveExplicitSolver.h
goss/include/goss/ImplicitEuler.h
goss/include/goss/goss.h
goss/include/goss/GRL2.h
goss/include/goss/ExplicitEuler.h
goss/include/goss/ImplicitODESolver.h
goss/include/goss/BasicImplicitEuler.h
goss/include/goss/ODESystemSolver.h
goss/include/goss/ParameterizedODE.h
goss/include/goss/constants.h
goss/include/goss/ODE.h
goss/include/goss/GRL1.h
goss/include/goss/RL2.h
goss/include/goss/ThetaSolver.h
goss/include/goss/RL1.h
goss/include/goss/ESDIRK4O32.h
goss/include/goss/version.h
goss/include/goss/ODESolver.h
goss/include/goss/DoubleVector.h
goss/include/goss/RK4.h
goss/include/goss/RKF32.h
goss/include/goss/ESDIRK23a.h
goss/include/goss/AdaptiveImplicitSolver.h
goss/include/goss/types.h
goss/include/goss/RK2.h
